bk_plugin_framework/__init__.py
bk_plugin_framework/__version__.py
bk_plugin_framework/constants.py
bk_plugin_framework/envs.py
bk_plugin_framework/hub/__init__.py
bk_plugin_framework/kit/__init__.py
bk_plugin_framework/kit/api.py
bk_plugin_framework/kit/authentication.py
bk_plugin_framework/kit/decorators.py
bk_plugin_framework/kit/plugin.py
bk_plugin_framework/metrics.py
bk_plugin_framework/runtime/__init__.py
bk_plugin_framework/runtime/callback/__init__.py
bk_plugin_framework/runtime/callback/api.py
bk_plugin_framework/runtime/callback/apps.py
bk_plugin_framework/runtime/callback/celery/__init__.py
bk_plugin_framework/runtime/callback/celery/queues.py
bk_plugin_framework/runtime/callback/celery/tasks.py
bk_plugin_framework/runtime/callback/migrations/__init__.py
bk_plugin_framework/runtime/callbacker.py
bk_plugin_framework/runtime/executor.py
bk_plugin_framework/runtime/loghub/__init__.py
bk_plugin_framework/runtime/loghub/admin.py
bk_plugin_framework/runtime/loghub/apps.py
bk_plugin_framework/runtime/loghub/log.py
bk_plugin_framework/runtime/loghub/migrations/0001_initial.py
bk_plugin_framework/runtime/loghub/migrations/__init__.py
bk_plugin_framework/runtime/loghub/models.py
bk_plugin_framework/runtime/schedule/__init__.py
bk_plugin_framework/runtime/schedule/admin.py
bk_plugin_framework/runtime/schedule/apps.py
bk_plugin_framework/runtime/schedule/celery/__init__.py
bk_plugin_framework/runtime/schedule/celery/beat.py
bk_plugin_framework/runtime/schedule/celery/queues.py
bk_plugin_framework/runtime/schedule/celery/tasks.py
bk_plugin_framework/runtime/schedule/migrations/0001_initial.py
bk_plugin_framework/runtime/schedule/migrations/0002_schedule_finish_at.py
bk_plugin_framework/runtime/schedule/migrations/0003_auto_20210830_1945.py
bk_plugin_framework/runtime/schedule/migrations/0004_schedule_scheduling.py
bk_plugin_framework/runtime/schedule/migrations/0005_schedule_err.py
bk_plugin_framework/runtime/schedule/migrations/__init__.py
bk_plugin_framework-2.3.3.dist-info/METADATA
bk_plugin_framework-2.3.3.dist-info/WHEEL
bk_plugin_framework-2.3.3.dist-info/RECORD
