Metadata-Version: 2.1
Name: bk-plugin-framework
Version: 2.3.3
Summary: bk plugin python framework
License: MIT
Author: Your Name
Author-email: you@example.com
Requires-Python: >=3.8.0,<4.0.0
Classifier: License :: OSI Approved :: MIT License
Classifier: Programming Language :: Python :: 3
Classifier: Programming Language :: Python :: 3.8
Classifier: Programming Language :: Python :: 3.9
Classifier: Programming Language :: Python :: 3.10
Classifier: Programming Language :: Python :: 3.11
Classifier: Programming Language :: Python :: 3.12
Classifier: Programming Language :: Python :: 3.13
Requires-Dist: apigw-manager[extra] (>=1.0.6,<4)
Requires-Dist: bk-plugin-runtime (==2.1.2)
Requires-Dist: jsonschema (>=2.5.0,<5.0.0)
Requires-Dist: pydantic (>=1.0,<3)
Requires-Dist: werkzeug (>=2.0.0,<4.0)
